chatcell/__init__.py
chatcell/auth.py
chatcell/base.py
chatcell/config.py
chatcell/logging.py
chatcell/middleware.py
chatcell/server.py
chatcell/types.py
chatcell-0.0.1.dist-info/METADATA
chatcell-0.0.1.dist-info/WHEEL
chatcell-0.0.1.dist-info/RECORD
