Metadata-Version: 2.1
Name: chatcell
Version: 0.0.1
Summary: A python framework to create your personal AI assistant.
Author: jiandong
Author-email: jiandong@weanalyze.co
Requires-Python: >=3.10,<4.0
Classifier: Programming Language :: Python :: 3
Classifier: Programming Language :: Python :: 3.10
Classifier: Programming Language :: Python :: 3.11
Requires-Dist: fastapi (>=0.95.1,<0.96.0)
Requires-Dist: pydantic (>=1.10.7,<2.0.0)
Requires-Dist: python-dotenv (>=1.0.0,<2.0.0)
Requires-Dist: rich (>=13.3.5,<14.0.0)
Requires-Dist: sse-starlette (>=1.3.4,<2.0.0)
Requires-Dist: typing-extensions (>=4.5.0,<5.0.0)
Requires-Dist: uvicorn (>=0.22.0,<0.23.0)
